topsis_rohitThapar_102003482/topsis.py
topsis_rohitThapar_102003482-1.0.0.dist-info/LICENSE.txt
topsis_rohitThapar_102003482-1.0.0.dist-info/METADATA
topsis_rohitThapar_102003482-1.0.0.dist-info/WHEEL
topsis_rohitThapar_102003482-1.0.0.dist-info/entry_points.txt
topsis_rohitThapar_102003482-1.0.0.dist-info/top_level.txt
topsis_rohitThapar_102003482-1.0.0.dist-info/RECORD
